{
  "req_uuid": "f625e7c4-b093-47da-b4a7-ac2370405e21",
  "client_req_id": "faf7669d3a454cf192e214fd69aa7af9",
  "timestamp": 1774578270689,
  "remote": "127.0.0.1",
  "content_length": 119371,
  "headers": {
    "Host": "127.0.0.1:5000",
    "User-Agent": "UnityPlayer/6000.3.9f1 (UnityWebRequest/1.0, libcurl/8.10.1-DEV)",
    "Accept": "*/*",
    "Accept-Encoding": "deflate, gzip",
    "Content-Type": "multipart/form-data; boundary=\"TirLPLjSVJdEhoDcJWpKyy52W2DeEtVJGgZ2Fqju\"",
    "X-Unity-Version": "6000.3.9f1",
    "Content-Length": "119371"
  },
  "form_keys": [
    "client_req_id"
  ],
  "files_keys": [
    "file"
  ],
  "saved_path": "C:\\Users\\555a\\AppData\\Local\\Temp\\tmprxm5va17.wav",
  "saved_size": 119006,
  "sha256": "236d9165fff4ce6234ea0dbddc25ddb9f21290d3130fc5839f3781c90bdd75e6",
  "deepgram_request_id": null,
  "deepgram_log_file": null,
  "deepgram_status": "no_key",
  "deepgram_error": "DEEPGRAM_API_KEY not set",
  "deepgram_attempt_count": 0,
  "deepgram_confidence": null,
  "deepgram_http_status": null,
  "transcript_len": 0,
  "response_summary": {
    "req_uuid": "f625e7c4-b093-47da-b4a7-ac2370405e21",
    "client_req_id": "faf7669d3a454cf192e214fd69aa7af9",
    "deepgram_status": "no_key",
    "deepgram_called": false,
    "deepgram_request_id": null,
    "deepgram_log_file": null,
    "transcript_source": "none",
    "transcript_is_empty": true,
    "latency_ms": 65
  }
}