{
  "metadata": {
    "transaction_key": "deprecated",
    "request_id": "4260ecad-3839-48d7-b184-b1251388aac7",
    "sha256": "3a1de831ceda69c11e3ab276bac31be2238444aecc55f42234f7a96db3089fb0",
    "created": "2026-03-25T01:56:22.084Z",
    "duration": 4.57,
    "channels": 1,
    "models": [
      "3c79c76c-d186-482b-89d8-8b005a5e5917"
    ],
    "model_info": {
      "3c79c76c-d186-482b-89d8-8b005a5e5917": {
        "name": "general-nova-3",
        "version": "2025-09-24.25124",
        "arch": "nova-3"
      }
    }
  },
  "results": {
    "channels": [
      {
        "alternatives": [
          {
            "transcript": "내가더잘할게사랑해요",
            "confidence": 0.98828125,
            "words": [
              {
                "word": "내가",
                "start": 0.48,
                "end": 0.88,
                "confidence": 0.98828125
              },
              {
                "word": "더",
                "start": 0.88,
                "end": 1.1999999,
                "confidence": 0.99902344
              },
              {
                "word": "잘할게",
                "start": 1.1999999,
                "end": 2.4799998,
                "confidence": 0.51782227
              },
              {
                "word": "사랑해요",
                "start": 2.72,
                "end": 4.3199997,
                "confidence": 0.95581055
              }
            ]
          }
        ]
      }
    ]
  }
}